{
	"app":	{
		"bundleName":	"com.example.enjoyarkuix",
		"vendor":	"example",
		"versionCode":	5000000,
		"versionName":	"1.0.0",
		"icon":	"$media:app_icon",
		"label":	"$string:app_name",
		"apiReleaseType":	"Canary1",
		"compileSdkVersion":	"6.0.0.34",
		"targetAPIVersion":	16,
		"minAPIVersion":	16,
		"compileSdkType":	"OpenHarmony",
		"appEnvironments":	[],
		"bundleType":	"app",
		"buildMode":	"debug",
		"debug":	true,
		"iconId":	134217729,
		"labelId":	134217728
	},
	"module":	{
		"name":	"dynamicHapTwo",
		"type":	"feature",
		"description":	"$string:module_desc",
		"mainElement":	"DynamicHapTwoAbility",
		"deviceTypes":	["default"],
		"deliveryWithInstall":	true,
		"installationFree":	false,
		"pages":	"$profile:main_pages",
		"abilities":	[{
				"name":	"DynamicHapTwoAbility",
				"srcEntry":	"./ets/dynamichaptwoability/DynamicHapTwoAbility.ets",
				"description":	"$string:DynamicHapTwoAbility_desc",
				"icon":	"$media:layered_image",
				"label":	"$string:DynamicHapTwoAbility_label",
				"startWindowIcon":	"$media:startIcon",
				"startWindowBackground":	"$color:start_window_background",
				"exported":	true,
				"descriptionId":	134217730,
				"iconId":	134217737,
				"labelId":	134217731,
				"startWindowIconId":	134217738,
				"startWindowBackgroundId":	134217733
			}],
		"packageName":	"dynamichaptwo",
		"virtualMachine":	"ark12.0.6.0",
		"compileMode":	"esmodule",
		"dependencies":	[],
		"descriptionId":	134217732
	}
}